audite/__init__.py
audite/__main__.py
audite/auditor.py
audite-0.4.5.dist-info/LICENSE
audite-0.4.5.dist-info/METADATA
audite-0.4.5.dist-info/WHEEL
audite-0.4.5.dist-info/entry_points.txt
audite-0.4.5.dist-info/top_level.txt
audite-0.4.5.dist-info/RECORD
