Metadata-Version: 2.1
Name: audite
Version: 0.4.5
Summary: Instant data auditing for SQLite
Home-page: https://github.com/chrisfrank/audite
Author: Chris Frank
Project-URL: Bug Reports, https://github.com/chrisfrank/audite
Project-URL: Source, https://github.com/chrisfrank/audite
Keywords: sqlite,audit,history,change-data-capture,change feed
Classifier: Development Status :: 3 - Alpha
Classifier: Intended Audience :: Developers
Classifier: Topic :: Software Development :: Build Tools
Classifier: Programming Language :: Python :: 3
Classifier: Programming Language :: Python :: 3.7
Classifier: Programming Language :: Python :: 3.8
Classifier: Programming Language :: Python :: 3.9
Classifier: Programming Language :: Python :: 3.10
Classifier: Programming Language :: Python :: 3.11
Classifier: Programming Language :: Python :: 3 :: Only
Requires-Python: >=3.7, <4
License-File: LICENSE
